rye_demo/__init__.py
rye_demo-0.1.2.dist-info/METADATA
rye_demo-0.1.2.dist-info/WHEEL
rye_demo-0.1.2.dist-info/RECORD
