Metadata-Version: 2.1
Name: rye-demo
Version: 0.1.2
Summary: Add your description here
Author-email: Meng Xiangzhuo <aumo@foxmail.com>
Requires-Python: >=3.8
Requires-Dist: flask>=3.0.0
